Workbook

Sheet Instrucciones
A1: Libro de trabajo de la AE2 · Proyecto Final de Grado 2026
A2: Universidad de la Cuenca del Plata · Ingeniería en Sistemas de Información · Comisión A · Sede Posadas · Docente Titular: PosDr. Darío Ezequiel Díaz · ISI-PFG-2026C2-AE2-v02
A4: Para qué sirve este libro | B4: Reúne, en un solo archivo versionable, los instrumentos de la Unidad Dos que producen el Capítulo III y alimentan los Capítulos V y X: el catálogo de requisitos, la matriz de trazabilidad, el filtro de entidades, el registro de reglas, el glosario, el plan de iteraciones y el dimensionamiento de recursos. La hoja «Panel» controla sola el estado de completitud y avisa qué falta.
A5: Dónde se guarda | B5: En el repositorio del equipo, carpeta /03-requisitos, con la nomenclatura de la cátedra: AAAAMMDD_CatalogoRequisitos_Equipo_vN.xlsx. Se versiona cada vez que se cierra un bloque de filas, no una sola vez antes de la entrega.
A6: Qué celdas se completan | B6: Todas las celdas blancas y grises de cada hoja, a partir de la fila 5. Las filas sombreadas en ocre son ejemplos resueltos sobre el caso conductor «Santa Ana»: se leen, no se copian, y se borran antes de entregar. Las columnas de control, sombreadas en amarillo, contienen fórmulas: no se escriben.
A7: Cómo se usan las listas desplegables | B7: Las columnas de tipo, prioridad y estado admiten sólo los valores de la lista. Si un valor es rechazado, es porque la categoría no corresponde a la clasificación de la cátedra.
A8: Qué mira la corrección | B8: Que cada requisito tenga sus seis campos, que su criterio de aceptación sea un procedimiento ejecutable por un tercero, que la trazabilidad cierre en doble vía y que el conjunto de los requisitos «Must» coincida con el producto mínimo viable del apartado V.5.
A9: Orden de trabajo sugerido | B9: 1) Entidades y Reglas, en el taller. 2) Trazabilidad, con los hallazgos de la AE1 codificados H-01, H-02… 3) Catálogo, derivando requisitos de esos hallazgos. 4) Sesión de validación con el referente y actualización de los estados. 5) Iteraciones y Recursos, ya con el catálogo cerrado.
A10: Advertencia | B10: Ante divergencia entre este libro y la Consigna ISI-PFG-2026C2-AE2-v02, prevalece la consigna. Ante divergencia entre la consigna y la Resolución Rectoral UCP N.º 97/23, prevalece la Resolución.
A12: Leyenda de colores
A13: Ocre | B13: Fila de ejemplo resuelta sobre el caso «Santa Ana». Se borra antes de entregar.
A14: Amarillo | B14: Celda con fórmula de control. No se escribe.
A15: Blanco y gris | B15: Celdas que completa el equipo.

Sheet Catálogo
A1: Catálogo de requisitos · apartado III.5 del informe
A2: Una fila por requisito, con los seis campos completos. Regla de cómputo: un requisito sin criterio de aceptación comprobable no se computa, por bien redactado que esté. Antes de cerrar una fila, aplique la prueba del compañero: otro integrante debe poder decir, en diez segundos, cómo verificaría el requisito.
A4: ID | B4: Enunciado | C4: Tipo | D4: Categoría (si es no funcional) | E4: Prioridad | F4: Motivo de la prioridad | G4: Criterio de aceptación (condición, acción, resultado con valores) | H4: Trazabilidad (H-xx o acta) | I4: Estado de validación | J4: Iteración prevista | K4: ¿Integra el MVP? | L4: Control de completitud
A5: RNF-01 | B5: La captura de pesadas opera sin conectividad y sincroniza en diferido al restablecerse el enlace, sin pérdida ni duplicación de registros. | C5: No funcional | D5: Fiabilidad | E5: Must | F5: Condiciona la arquitectura completa: excluye una solución íntegramente web. | G5: Jornada de prueba con un puesto desconectado durante la operación; al reconectar, los registros aparecen completos y únicos en la consolidación, y el conteo coincide con el papel del puesto. | H5: H-02 · observación de campo del 19/08: conectividad intermitente en los tres puestos (Cap. II, ap. II.3) | I5: Validado | J5: 1 | K5: Sí | L5: =IF($A5="","",IF(COUNTBLANK($B5:$C5)+COUNTBLANK($E5:$H5)>0,"Faltan campos",IF(AND($C5="No funcional",$D5=""),"Falta categoría",IF($K5="","Falta definir si integra el MVP","Fila completa")))) -> Fila completa
L6: =IF($A6="","",IF(COUNTBLANK($B6:$C6)+COUNTBLANK($E6:$H6)>0,"Faltan campos",IF(AND($C6="No funcional",$D6=""),"Falta categoría",IF($K6="","Falta definir si integra el MVP","Fila completa"))))
L7: =IF($A7="","",IF(COUNTBLANK($B7:$C7)+COUNTBLANK($E7:$H7)>0,"Faltan campos",IF(AND($C7="No funcional",$D7=""),"Falta categoría",IF($K7="","Falta definir si integra el MVP","Fila completa"))))
L8: =IF($A8="","",IF(COUNTBLANK($B8:$C8)+COUNTBLANK($E8:$H8)>0,"Faltan campos",IF(AND($C8="No funcional",$D8=""),"Falta categoría",IF($K8="","Falta definir si integra el MVP","Fila completa"))))
L9: =IF($A9="","",IF(COUNTBLANK($B9:$C9)+COUNTBLANK($E9:$H9)>0,"Faltan campos",IF(AND($C9="No funcional",$D9=""),"Falta categoría",IF($K9="","Falta definir si integra el MVP","Fila completa"))))
L10: =IF($A10="","",IF(COUNTBLANK($B10:$C10)+COUNTBLANK($E10:$H10)>0,"Faltan campos",IF(AND($C10="No funcional",$D10=""),"Falta categoría",IF($K10="","Falta definir si integra el MVP","Fila completa"))))
L11: =IF($A11="","",IF(COUNTBLANK($B11:$C11)+COUNTBLANK($E11:$H11)>0,"Faltan campos",IF(AND($C11="No funcional",$D11=""),"Falta categoría",IF($K11="","Falta definir si integra el MVP","Fila completa"))))
L12: =IF($A12="","",IF(COUNTBLANK($B12:$C12)+COUNTBLANK($E12:$H12)>0,"Faltan campos",IF(AND($C12="No funcional",$D12=""),"Falta categoría",IF($K12="","Falta definir si integra el MVP","Fila completa"))))
L13: =IF($A13="","",IF(COUNTBLANK($B13:$C13)+COUNTBLANK($E13:$H13)>0,"Faltan campos",IF(AND($C13="No funcional",$D13=""),"Falta categoría",IF($K13="","Falta definir si integra el MVP","Fila completa"))))
L14: =IF($A14="","",IF(COUNTBLANK($B14:$C14)+COUNTBLANK($E14:$H14)>0,"Faltan campos",IF(AND($C14="No funcional",$D14=""),"Falta categoría",IF($K14="","Falta definir si integra el MVP","Fila completa"))))
L15: =IF($A15="","",IF(COUNTBLANK($B15:$C15)+COUNTBLANK($E15:$H15)>0,"Faltan campos",IF(AND($C15="No funcional",$D15=""),"Falta categoría",IF($K15="","Falta definir si integra el MVP","Fila completa"))))
L16: =IF($A16="","",IF(COUNTBLANK($B16:$C16)+COUNTBLANK($E16:$H16)>0,"Faltan campos",IF(AND($C16="No funcional",$D16=""),"Falta categoría",IF($K16="","Falta definir si integra el MVP","Fila completa"))))
L17: =IF($A17="","",IF(COUNTBLANK($B17:$C17)+COUNTBLANK($E17:$H17)>0,"Faltan campos",IF(AND($C17="No funcional",$D17=""),"Falta categoría",IF($K17="","Falta definir si integra el MVP","Fila completa"))))
... L201: =IF($A201="","",IF(COUNTBLANK($B201:$C201)+COUNTBLANK($E201:$H201)>0,"Faltan campos",IF(AND($C201="No funcional",$D201=""),"Falta categoría",IF($K201="","Falta definir si integra el MVP","Fila completa"))))

Sheet Trazabilidad
A1: Matriz de trazabilidad · hallazgo de la AE1 → requisito
A2: Se verifica en doble vía. Todo requisito llega a un hallazgo; todo hallazgo llega a un requisito o a una justificación expresa de por qué no derivó ninguno. El silencio no es una decisión.
A4: Código (H-01, H-02…) | B4: Hallazgo de la AE1 (dato y valor) | C4: Fuente (apartado del Cap. II o acta) | D4: Requisito(s) derivado(s) | E4: Si no deriva: justificación | F4: Control de la doble vía
A5: H-04 | B5: Demora promedio de once días entre el cierre de quincena y la acreditación al productor, medida sobre veinticuatro quincenas. | C5: Cap. II, ap. II.3 · registro de liquidaciones del ejercicio | D5: RF-02 | F5: =IF($A5="","",IF(AND($D5="",$E5=""),"Hallazgo sin destino",IF($D5="","Sin requisito, justificado","Deriva requisito"))) -> Deriva requisito
F6: =IF($A6="","",IF(AND($D6="",$E6=""),"Hallazgo sin destino",IF($D6="","Sin requisito, justificado","Deriva requisito")))
F7: =IF($A7="","",IF(AND($D7="",$E7=""),"Hallazgo sin destino",IF($D7="","Sin requisito, justificado","Deriva requisito")))
F8: =IF($A8="","",IF(AND($D8="",$E8=""),"Hallazgo sin destino",IF($D8="","Sin requisito, justificado","Deriva requisito")))
F9: =IF($A9="","",IF(AND($D9="",$E9=""),"Hallazgo sin destino",IF($D9="","Sin requisito, justificado","Deriva requisito")))
F10: =IF($A10="","",IF(AND($D10="",$E10=""),"Hallazgo sin destino",IF($D10="","Sin requisito, justificado","Deriva requisito")))
F11: =IF($A11="","",IF(AND($D11="",$E11=""),"Hallazgo sin destino",IF($D11="","Sin requisito, justificado","Deriva requisito")))
F12: =IF($A12="","",IF(AND($D12="",$E12=""),"Hallazgo sin destino",IF($D12="","Sin requisito, justificado","Deriva requisito")))
F13: =IF($A13="","",IF(AND($D13="",$E13=""),"Hallazgo sin destino",IF($D13="","Sin requisito, justificado","Deriva requisito")))
F14: =IF($A14="","",IF(AND($D14="",$E14=""),"Hallazgo sin destino",IF($D14="","Sin requisito, justificado","Deriva requisito")))
F15: =IF($A15="","",IF(AND($D15="",$E15=""),"Hallazgo sin destino",IF($D15="","Sin requisito, justificado","Deriva requisito")))
F16: =IF($A16="","",IF(AND($D16="",$E16=""),"Hallazgo sin destino",IF($D16="","Sin requisito, justificado","Deriva requisito")))
F17: =IF($A17="","",IF(AND($D17="",$E17=""),"Hallazgo sin destino",IF($D17="","Sin requisito, justificado","Deriva requisito")))
... F61: =IF($A61="","",IF(AND($D61="",$E61=""),"Hallazgo sin destino",IF($D61="","Sin requisito, justificado","Deriva requisito")))

Sheet Entidades
A1: Lista filtrada de entidades del dominio · Instrumento 28
A2: Cada candidata pasa por el filtro de las tres preguntas. Las descartadas no se borran: se reclasifican, porque los descartes de hoy son las preguntas del glosario de mañana.
A4: Candidata (sustantivo de la organización) | B4: ¿Identidad propia? | C4: ¿Datos y reglas propios? | D4: ¿Dentro del recorte? | E4: Veredicto | F4: Fuente que la acredita | G4: Relaciones principales
A5: Pesada (el referente dice «romaneo» en dos entrevistas: ver Glosario) | B5: Sí: «esta pesada, la del camión de García del martes» | C5: Sí: kilos, humedad, fecha, balanza; reglas de validez y de quincena abierta | D5: Sí: origen de tres líneas de base del diagnóstico | E5: Entidad | F5: Hoja «pesadas por quincena» de la planilla (foto 19/08) | G5: Una quincena agrupa muchas pesadas; una pesada puede originar un reclamo

Sheet Reglas
A1: Registro de reglas de negocio · Instrumento 29
A2: Regla y requisito derivado deben citar la misma fuente: esa coincidencia es la trazabilidad que la dimensión 1 de la rúbrica verifica.
A4: Código | B4: Tipo | C4: Enunciado verificable | D4: Fuente | E4: Estado | F4: Requisito derivado (ID)
A5: R-01 | B5: Restricción | C5: Una quincena cerrada no admite nuevas pesadas ni modificación de las existentes; la reapertura requiere autorización registrada del administrador. | D5: Entrevista del 19/08 · práctica del cierre | E5: Validada | F5: RF-03
A6: R-02
A7: R-03
A8: R-04
A9: R-05
A10: R-06
A11: R-07
A12: R-08
A13: R-09
A14: R-10
A15: R-11
A16: R-12
A17: R-13
... A40: R-36

Sheet Glosario
A1: Glosario del dominio · Instrumento 30
A2: Vocabulario normativo del informe completo y, más adelante, de las tablas del sistema. La entrada más valiosa es la del término en disputa: el que dos personas de la organización usan distinto.
A4: Término (como lo usa la organización) | B4: Definición operativa (una o dos oraciones) | C4: Sinónimos y falsos amigos detectados | D4: Fuente (quién lo usa así) | E4: ¿En disputa?
A5: Romaneo | B5: Registro de la operación de pesaje de un camión en una balanza, con kilos, humedad y fecha. El equipo lo denomina «pesada». | C5: El administrativo dice «boleta»; el productor, «ticket». Los tres nombran el mismo objeto. | D5: Referente y encargado de balanza (entrevistas del 19/08) | E5: Sí

Sheet Iteraciones
A1: Plan de iteraciones y presupuesto de horas · Capítulo V
A2: El cronograma se construye sobre el presupuesto efectivo de horas-persona y se alinea con la cadencia de artefactos: v1 en la semana 8, v2 en la semana 11, v3 en la semana 13 y versión funcional congelada en la semana 14.
A4: Iteración | B4: Desde | C4: Hasta | D4: Objetivo verificable | E4: Requisitos comprometidos (ID) | F4: Entregable de cierre | G4: Horas asignadas
A5: 1
A6: 2
A7: 3
A8: 4
A9: 5
A10: 6
A11: 7
A12: 8
A15: Presupuesto de horas-persona
A16: Integrantes del equipo
A17: Horas semanales reales por integrante (declaradas, no deseadas)
A18: Semanas del período
A19: Presupuesto total | B19: =IF(COUNT(B16:B18)=3,B16*B17*B18,"")
A20: Reducción prevista por exámenes y feriados (horas)
A21: Presupuesto efectivo resultante | B21: =IF(B19="","",B19-N(B20))
A22: Horas ya asignadas a iteraciones | B22: =SUM(G5:G12) -> 0
A23: Margen disponible | B23: =IF(B21="","",B21-B22)
A25: Cláusula de contingencia (exigencia vii de la consigna)
A26: Si el presupuesto de horas cae un tercio, se posterga
A27: Criterio de redistribución, según el acta de constitución
A28: Qué no se sacrifica en ningún caso | B28: La trazabilidad del catálogo y la ejecutabilidad del prototipo v1: son condiciones de cómputo.

Sheet Recursos
A1: Dimensionamiento de recursos · Capítulo X
A2: Cada asignación con su justificación y su fuente. Toda cifra de costo responde las tres preguntas: quién la produjo, con qué método y sobre qué universo, y para qué período de referencia. No se promedian cifras de universos distintos.
A4: Clase | B4: Concepto | C4: Cantidad | D4: Unidad | E4: Costo unitario | F4: Subtotal | G4: Fuente, período y justificación
A5: Humanos | B5: Perfil de desarrollo (equipo del proyecto) | C5: 160 | D5: hora | E5: 0 | F5: =IF(OR($C5="",$E5=""),"",$C5*$E5) -> 0 | G5: Costo de hora de referencia del sector SSI. Fuente: [organismo, relevamiento, período]. Se declara el universo y no se promedian fuentes distintas.
F6: =IF(OR($C6="",$E6=""),"",$C6*$E6)
F7: =IF(OR($C7="",$E7=""),"",$C7*$E7)
F8: =IF(OR($C8="",$E8=""),"",$C8*$E8)
F9: =IF(OR($C9="",$E9=""),"",$C9*$E9)
F10: =IF(OR($C10="",$E10=""),"",$C10*$E10)
F11: =IF(OR($C11="",$E11=""),"",$C11*$E11)
F12: =IF(OR($C12="",$E12=""),"",$C12*$E12)
F13: =IF(OR($C13="",$E13=""),"",$C13*$E13)
F14: =IF(OR($C14="",$E14=""),"",$C14*$E14)
F15: =IF(OR($C15="",$E15=""),"",$C15*$E15)
F16: =IF(OR($C16="",$E16=""),"",$C16*$E16)
F17: =IF(OR($C17="",$E17=""),"",$C17*$E17)
... F34: =IF(OR($C34="",$E34=""),"",$C34*$E34)
E36: Total general | F36: =SUM(F5:F34) -> 0
E37: Horas humanas comprometidas | F37: =SUMIF($A$5:$A$34,"Humanos",$C$5:$C$34) -> 160
E38: Coherencia con el Capítulo V | F38: =IF(Iteraciones!$B$21="","Falta el presupuesto efectivo",IF(F37=Iteraciones!$B$21,"Coherente",IF(F37>Iteraciones!$B$21,"Excede el presupuesto","No agota el presupuesto: revisar"))) -> Falta el presupuesto efectivo

Sheet Panel
A1: Panel de control de la entrega
A2: Los valores se calculan solos a partir de las demás hojas. Ninguna celda de esta hoja se escribe a mano. Recórrala la noche anterior a la entrega: cada línea en rojo es una observación previsible en la devolución.
A4: Indicador | B4: Valor | C4: Qué debe verificarse
A5: Requisitos registrados | B5: =COUNTIF(Catálogo!$A$5:$A$201,"?*") -> 1 | C5: Un catálogo de menos de ocho requisitos rara vez cubre el alcance declarado.
A6: Requisitos con criterio de aceptación | B6: =COUNTIFS(Catálogo!$A$5:$A$201,"?*",Catálogo!$G$5:$G$201,"?*") -> 1 | C6: Debe coincidir con el total. Un requisito sin criterio no se computa.
A7: Requisitos trazados a un hallazgo o acta | B7: =COUNTIFS(Catálogo!$A$5:$A$201,"?*",Catálogo!$H$5:$H$201,"?*") -> 1 | C7: Debe coincidir con el total. Sin origen, el requisito no ingresa al catálogo.
A8: Requisitos no funcionales | B8: =COUNTIFS(Catálogo!$A$5:$A$201,"?*",Catálogo!$C$5:$C$201,"No funcional") -> 1 | C8: Un catálogo sin requisitos no funcionales no decidió arquitectura.
A9: No funcionales sin categoría declarada | B9: =COUNTIFS(Catálogo!$C$5:$C$201,"No funcional",Catálogo!$D$5:$D$201,"") -> 0 | C9: Debe ser cero.
A10: Requisitos «Must» | B10: =COUNTIFS(Catálogo!$A$5:$A$201,"?*",Catálogo!$E$5:$E$201,"Must") -> 1 | C10: Priorizar es nombrar lo que no se hará. Si casi todo es «Must», no se priorizó.
A11: Requisitos declarados dentro del MVP | B11: =COUNTIFS(Catálogo!$A$5:$A$201,"?*",Catálogo!$K$5:$K$201,"Sí") -> 1 | C11: Debe coincidir con la cantidad de «Must».
A12: Coherencia entre «Must» y producto mínimo viable | B12: =IF(COUNTIFS(Catálogo!$A$5:$A$201,"?*",Catálogo!$E$5:$E$201,"Must")=COUNTIFS(Catálogo!$A$5:$A$201,"?*",Catálogo!$K$5:$K$201,"Sí"),"Coherente","REVISAR") -> Coherente | C12: Si dice REVISAR, uno de los dos apartados está mal escrito: el catálogo o el V.5.
A13: Requisitos validados con el referente | B13: =COUNTIFS(Catálogo!$A$5:$A$201,"?*",Catálogo!$I$5:$I$201,"Validado") -> 1 | C13: Un requisito redactado y no validado carece de valor probatorio.
A14: Filas del catálogo con campos faltantes | B14: =COUNTIF(Catálogo!$L$5:$L$201,"Faltan campos")+COUNTIF(Catálogo!$L$5:$L$201,"Falta categoría")+COUNTIF(Catálogo!$L$5:$L$201,"Falta definir si integra el MVP") -> 0 | C14: Debe ser cero antes de exportar el PDF.
A15: Hallazgos de la AE1 registrados | B15: =COUNTIF(Trazabilidad!$A$5:$A$61,"?*") -> 1 | C15: Todo hallazgo del Capítulo II que sostuvo el diagnóstico debería estar.
A16: Hallazgos sin requisito ni justificación | B16: =COUNTIF(Trazabilidad!$F$5:$F$61,"Hallazgo sin destino") -> 0 | C16: Debe ser cero. El silencio no es una decisión.
A17: Entidades aceptadas en el modelo del dominio | B17: =COUNTIF(Entidades!$E$5:$E$45,"Entidad") -> 1 | C17: Cada una debe tener su fuente en la columna correspondiente.
A18: Candidatas evaluadas y reclasificadas | B18: =COUNTIF(Entidades!$A$5:$A$45,"?*")-COUNTIF(Entidades!$E$5:$E$45,"Entidad") -> 0 | C18: Los descartes documentados son los que permiten defender la delimitación.
A19: Reglas de negocio registradas | B19: =COUNTIF(Reglas!$C$5:$C$40,"?*") -> 1 | C19: Mínimo exigido en el taller de la Clase 8: tres reglas enunciadas de modo verificable.
A20: Reglas todavía pendientes de validación | B20: =COUNTIF(Reglas!$E$5:$E$40,"Pendiente")+COUNTIF(Reglas!$E$5:$E$40,"En disputa") -> 0 | C20: Toda regla pendiente pasa a la guía de la sesión de validación.
A21: Términos del glosario en disputa | B21: =COUNTIF(Glosario!$E$5:$E$45,"Sí") -> 1 | C21: Se resuelven con el referente y se cierran con una definición acordada.
A22: Horas asignadas a iteraciones | B22: =SUM(Iteraciones!$G$5:$G$12) -> 0 | C22: Deben caber en el presupuesto efectivo de horas de la hoja Iteraciones.
A23: Coherencia entre recursos humanos y presupuesto de horas | B23: =Recursos!$F$38 -> Falta el presupuesto efectivo | C23: Las horas del Capítulo X y las del Capítulo V deben ser el mismo número.
A25: Condición material del cómputo
A26: Ninguna de estas cifras sustituye la comprobación del prototipo v1. La cátedra clona el repositorio en la etiqueta v1, sigue las instrucciones del archivo de lectura y ejecuta. Un esqueleto que no arranca, no compila o carece de instrucciones no se computa como entregado, con independencia de la calidad del documento que lo acompañe.
